{
  "appPageId" : "24c5e29f-4104-4963-99c7-e83810aa4532",
  "componentName" : "community_layout:sldsFlexibleLayout",
  "dataProviders" : [ ],
  "id" : "0caf3f39-93a6-4f87-9d1e-daa9907363a4",
  "label" : "Too Many Requests",
  "regions" : [ {
    "components" : [ {
      "componentAttributes" : {
        "backgroundImageConfig" : "",
        "backgroundImageOverlay" : "rgba(0,0,0,0)",
        "sectionConfig" : "{\"UUID\":\"0eed87e6-b9e0-4a11-a069-8f418b16ac70\",\"columns\":[{\"UUID\":\"9e46b4b0-9a5f-4a88-88a9-ca90d0ff3e49\",\"columnName\":\"Column 1\",\"columnKey\":\"col1\",\"columnWidth\":\"12\",\"seedComponents\":null}]}"
      },
      "componentName" : "community_layout:section",
      "id" : "0eed87e6-b9e0-4a11-a069-8f418b16ac70",
      "regions" : [ {
        "components" : [ {
          "componentAttributes" : {
            "richTextValue" : "<div style=\"display: flex; align-items: center; flex-direction: column; margin: 60px 25px 30px 25px;\">\n\t<div style=\"background-image: url(assets/img/tooManyRequests.svg); background-size: contain; height: 350px; width: 100%; background-repeat: no-repeat; background-position: center;\"></div>\n</div>\n<div style=\"margin: 0 25px; text-align: center;\">\n\t<h1 class=\"slds-text-heading_large\">Looks like the site is experiencing higher than usual demand&#8230;</h1>\n\t<p class=\"slds-text-heading_small\">Don't go anywhere. We'll redirect you in a moment.</p>\n</div>"
          },
          "componentName" : "community_builder:htmlEditor",
          "id" : "df5872ad-e2e8-414d-be8b-7190a21d2136",
          "renderPriority" : "NEUTRAL",
          "renditionMap" : { },
          "type" : "component"
        }, {
          "componentAttributes" : { },
          "componentName" : "experience_availability:autoRefresh",
          "id" : "1c62cebf-cbb7-405f-9a40-828abc833ac7",
          "renderPriority" : "NEUTRAL",
          "renditionMap" : { },
          "type" : "component"
        } ],
        "id" : "9e46b4b0-9a5f-4a88-88a9-ca90d0ff3e49",
        "regionLabel" : "Column 1",
        "regionName" : "col1",
        "renditionMap" : { },
        "type" : "region"
      } ],
      "renderPriority" : "NEUTRAL",
      "renditionMap" : { },
      "scopedBrandingSetId" : null,
      "type" : "component"
    } ],
    "id" : "1ee8c405-21b5-4e04-af53-15587d15ded1",
    "regionName" : "content",
    "type" : "region"
  } ],
  "themeLayoutType" : "ServiceNotAvailable",
  "type" : "view",
  "viewType" : "too-many-requests"
}